color_pprint/__init__.py
color_pprint/__main__.py
color_pprint/ansi/__init__.py
color_pprint-0.0.3.dist-info/LICENSE
color_pprint-0.0.3.dist-info/METADATA
color_pprint-0.0.3.dist-info/WHEEL
color_pprint-0.0.3.dist-info/top_level.txt
color_pprint-0.0.3.dist-info/RECORD
