Metadata-Version: 2.1
Name: color-pprint
Version: 0.0.3
Summary: A simple package to pretty-print lists dicts, tuples, etc. with color and highlight. (documentation SOON)
Home-page: https://github.com/mccoderpy/color-pprint
Author: mccoder.py
Author-email: mccuber04@outlook.de
License: MIT
Project-URL: Source, https://github.com/mccoderpy/color-pprint/
Project-URL: Support, https://discord.gg/sb69muSqsg
Project-URL: Issue Tracker, https://github.com/mccoderpy/color-pprint/issues
Classifier: Development Status :: 4 - Beta
Classifier: License :: OSI Approved :: MIT License
Classifier: Intended Audience :: Developers
Classifier: Natural Language :: English
Classifier: Operating System :: OS Independent
Classifier: Programming Language :: Python :: 3.5
Classifier: Programming Language :: Python :: 3.6
Classifier: Programming Language :: Python :: 3.7
Classifier: Programming Language :: Python :: 3.8
Classifier: Programming Language :: Python :: 3.9
Classifier: Programming Language :: Python :: 3.10
Classifier: Programming Language :: Python :: 3.11
Classifier: Programming Language :: Python :: 3.12
Classifier: Topic :: Printing
Classifier: Topic :: Software Development :: Libraries
Classifier: Topic :: Software Development :: Libraries :: Python Modules
Classifier: Topic :: Utilities
Classifier: Typing :: Typed
License-File: LICENSE
Requires-Dist: colorama (>=0.3.7)
Requires-Dist: multidict (>=5.1.0)
Requires-Dist: regex (>=0.1.20120103)
